annot/__init__.py
annot/_utils.py
annot/main.py
annots-0.1.2.dist-info/DESCRIPTION.rst
annots-0.1.2.dist-info/METADATA
annots-0.1.2.dist-info/RECORD
annots-0.1.2.dist-info/WHEEL
annots-0.1.2.dist-info/metadata.json
annots-0.1.2.dist-info/top_level.txt
