Metadata-Version: 2.0
Name: annots
Version: 0.1.2
Summary: annots is the package that allow to use Python 3.6 variable annotations in handy way.
Home-page: https://github.com/infernion/annots
Author: Sergey Khalymon
Author-email: sergiykhalimon@gmail.com
License: MIT license
Keywords: annots annotations typing
Platform: UNKNOWN
Classifier: Development Status :: 2 - Pre-Alpha
Classifier: Intended Audience :: Developers
Classifier: License :: OSI Approved :: MIT License
Classifier: Natural Language :: English
Classifier: Programming Language :: Python :: 3.6
